spitfire/__init__.py
spitfire-0.0.1.dist-info/WHEEL
spitfire-0.0.1.dist-info/METADATA
spitfire-0.0.1.dist-info/RECORD
