Metadata-Version: 1.1
Name: spitfire
Version: 0.0.1
Summary: Spitfire
Home-page: https://bitbucket.org/jouwomgeving/spitfire
Author: DK
Author-email: dkainama@jouwomgeving.nl
